README.rst
setup.py
Gentle.egg-info/PKG-INFO
Gentle.egg-info/SOURCES.txt
Gentle.egg-info/dependency_links.txt
Gentle.egg-info/entry_points.txt
Gentle.egg-info/requires.txt
Gentle.egg-info/top_level.txt
gentle/__init__.py
gentle/main.py
gentle/gt/__init__.py
gentle/gt/handler.py
gentle/gt/operations.py
gentle/gt/project.py
gentle/gt/utils.py